waiting/__init__.py
waiting/__version__.py
waiting/deadlines.py
waiting/exceptions.py
waiting-1.5.0.dist-info/METADATA
waiting-1.5.0.dist-info/WHEEL
waiting-1.5.0.dist-info/licenses/LICENSE
waiting-1.5.0.dist-info/RECORD
