Metadata-Version: 2.3
Name: waiting
Version: 1.5.0
Summary: Utility for waiting for stuff to happen
Project-URL: Homepage, https://github.com/getslash/waiting
Author-email: Rotem Yaari <vmalloc@gmail.com>
License: BSD 3-Clause License
License-File: LICENSE
Classifier: Programming Language :: Python :: 3.8
Classifier: Programming Language :: Python :: 3.9
Classifier: Programming Language :: Python :: 3.10
Classifier: Programming Language :: Python :: 3.11
Classifier: Programming Language :: Python :: 3.12
Requires-Python: >=3.8
Provides-Extra: testing
Requires-Dist: pyforge; extra == 'testing'
Requires-Dist: pytest; extra == 'testing'
